OiWiki202037/README.md
OiWiki202037/__init__.py
OiWiki202037/__main__.py
OiWiki202037/file.epub
OiWiki202037/index.html
OiWiki202037/css/__init__.py
OiWiki202037/css/annotations.css
OiWiki202037/css/main.css
OiWiki202037/css/normalize.css
OiWiki202037/css/popup.css
OiWiki202037/font/__init__.py
OiWiki202037/font/fontello.eot
OiWiki202037/font/fontello.svg
OiWiki202037/font/fontello.ttf
OiWiki202037/font/fontello.woff
OiWiki202037/img/__init__.py
OiWiki202037/img/annotator-glyph-sprite.png
OiWiki202037/img/annotator-icon-sprite.png
OiWiki202037/img/apple-touch-icon.png
OiWiki202037/img/cancelfullscreen.png
OiWiki202037/img/close.png
OiWiki202037/img/fullscreen.png
OiWiki202037/img/loader.gif
OiWiki202037/img/menu-icon.png
OiWiki202037/img/save.png
OiWiki202037/img/saved.png
OiWiki202037/img/settings-s.png
OiWiki202037/img/settings.png
OiWiki202037/img/star.png
OiWiki202037/js/__init__.py
OiWiki202037/js/epub.js
OiWiki202037/js/epub.min.js
OiWiki202037/js/epub.min.map
OiWiki202037/js/hooks.min.js
OiWiki202037/js/hooks.min.map
OiWiki202037/js/reader.js
OiWiki202037/js/reader.js.map
OiWiki202037/js/reader.min.js
OiWiki202037/js/reader.min.map
OiWiki202037/js/hooks/__init__.py
OiWiki202037/js/hooks/extensions/__init__.py
OiWiki202037/js/hooks/extensions/highlight.js
OiWiki202037/js/libs/__init__.py
OiWiki202037/js/libs/jquery.min.js
OiWiki202037/js/libs/localforage.min.js
OiWiki202037/js/libs/screenfull.js
OiWiki202037/js/libs/screenfull.min.js
OiWiki202037/js/libs/zip.min.js
OiWiki202037/js/plugins/__init__.py
OiWiki202037/js/plugins/hypothesis.js
OiWiki202037/js/plugins/search.js
oi_wiki_2020_3_7-2024.3.5.0.dist-info/METADATA
oi_wiki_2020_3_7-2024.3.5.0.dist-info/WHEEL
oi_wiki_2020_3_7-2024.3.5.0.dist-info/entry_points.txt
oi_wiki_2020_3_7-2024.3.5.0.dist-info/top_level.txt
oi_wiki_2020_3_7-2024.3.5.0.dist-info/RECORD
